uptick_splat/__init__.py
uptick_splat/config.py
uptick_splat/exceptions.py
uptick_splat/logging.py
uptick_splat/py.typed
uptick_splat/utils.py
uptick_splat-0.4.2.dist-info/METADATA
uptick_splat-0.4.2.dist-info/WHEEL
uptick_splat-0.4.2.dist-info/licenses/LICENSE.md
uptick_splat-0.4.2.dist-info/RECORD
