Metadata-Version: 2.4
Name: uptick-splat
Version: 0.4.2
Summary: Django library for invoking splat
Author-email: william chu <william.chu@uptickhq.com>
License-File: LICENSE.md
Requires-Python: >=3.12
Requires-Dist: boto3
Requires-Dist: django<5.2,>=5.0
Requires-Dist: playwright==1.43.0
